py50_streamlit_support/__init__.py
py50_streamlit_support/calculator.py
py50_streamlit_support/plot_settings.py
py50_streamlit_support/plotcurve.py
py50_streamlit_support/stats.py
py50_streamlit_support/utils.py
py50_streamlit_support-0.0.5.dist-info/METADATA
py50_streamlit_support-0.0.5.dist-info/WHEEL
py50_streamlit_support-0.0.5.dist-info/RECORD
